<annotation>
	<folder>sung_60</folder>
	<filename>image_00299.jpg</filename>
	<path>D:\data_project\50\sung_60\image_00299.jpg</path>
	<source>
		<database>Unknown</database>
	</source>
	<size>
		<width>641</width>
		<height>500</height>
		<depth>3</depth>
	</size>
	<segmented>0</segmented>
	<object>
		<name>water_lily</name>
		<pose>Unspecified</pose>
		<truncated>0</truncated>
		<difficult>0</difficult>
		<bndbox>
			<xmin>97</xmin>
			<ymin>38</ymin>
			<xmax>605</xmax>
			<ymax>472</ymax>
		</bndbox>
	</object>
</annotation>
