<annotation>
	<folder>anh_tuc_60</folder>
	<filename>image_03219.jpg</filename>
	<path>D:\data_project\50\anh_tuc_60\image_03219.jpg</path>
	<source>
		<database>Unknown</database>
	</source>
	<size>
		<width>500</width>
		<height>657</height>
		<depth>3</depth>
	</size>
	<segmented>0</segmented>
	<object>
		<name>californian_poppy</name>
		<pose>Unspecified</pose>
		<truncated>0</truncated>
		<difficult>0</difficult>
		<bndbox>
			<xmin>94</xmin>
			<ymin>170</ymin>
			<xmax>467</xmax>
			<ymax>493</ymax>
		</bndbox>
	</object>
</annotation>
