<annotation>
	<folder>hoa_su_60</folder>
	<filename>image_00781.jpg</filename>
	<path>D:\data_project\50\hoa_su_60\image_00781.jpg</path>
	<source>
		<database>Unknown</database>
	</source>
	<size>
		<width>676</width>
		<height>500</height>
		<depth>3</depth>
	</size>
	<segmented>0</segmented>
	<object>
		<name>frangipani</name>
		<pose>Unspecified</pose>
		<truncated>0</truncated>
		<difficult>0</difficult>
		<bndbox>
			<xmin>64</xmin>
			<ymin>84</ymin>
			<xmax>383</xmax>
			<ymax>354</ymax>
		</bndbox>
	</object>
	<object>
		<name>frangipani</name>
		<pose>Unspecified</pose>
		<truncated>0</truncated>
		<difficult>0</difficult>
		<bndbox>
			<xmin>322</xmin>
			<ymin>42</ymin>
			<xmax>631</xmax>
			<ymax>327</ymax>
		</bndbox>
	</object>
</annotation>
