<annotation>
	<folder>sen_60</folder>
	<filename>image_01864.jpg</filename>
	<path>D:\data_project\50\sen_60\image_01864.jpg</path>
	<source>
		<database>Unknown</database>
	</source>
	<size>
		<width>500</width>
		<height>511</height>
		<depth>3</depth>
	</size>
	<segmented>0</segmented>
	<object>
		<name>lotus</name>
		<pose>Unspecified</pose>
		<truncated>0</truncated>
		<difficult>0</difficult>
		<bndbox>
			<xmin>87</xmin>
			<ymin>65</ymin>
			<xmax>440</xmax>
			<ymax>395</ymax>
		</bndbox>
	</object>
</annotation>
